README.rst
setup.py
cataium/__init__.py
cataium/catcher.py
cataium_sample.egg-info/PKG-INFO
cataium_sample.egg-info/SOURCES.txt
cataium_sample.egg-info/dependency_links.txt
cataium_sample.egg-info/not-zip-safe
cataium_sample.egg-info/top_level.txt