Metadata-Version: 1.1
Name: cataium-sample
Version: 0.0.0.1
Summary: automation for app
Home-page: UNKNOWN
Author: JessieZhang
Author-email: zhangxuebupt@gmail.com
License: BSD
Keywords: cataium sample tools
Platform: UNKNOWN
Classifier: Development Status :: 3 - Alpha
Classifier: Environment :: MacOS X
Classifier: Intended Audience :: Developers
Classifier: License :: OSI Approved :: BSD License
Classifier: Operating System :: MacOS
Classifier: Programming Language :: Python
Classifier: Framework :: IPython
